barking/__init__.py
barking/foo.py
barking-0.0.1.dist-info/LICENSE
barking-0.0.1.dist-info/METADATA
barking-0.0.1.dist-info/WHEEL
barking-0.0.1.dist-info/top_level.txt
barking-0.0.1.dist-info/RECORD
