Metadata-Version: 2.1
Name: barking
Version: 0.0.1
Summary: This is a template repository for Python projects that use uv for their dependency management.
Author-email: Bryan Hann <nobody@nowhere.com>
Project-URL: Homepage, https://bryanhann.github.io/barking/
Project-URL: Repository, https://github.com/bryanhann/barking
Project-URL: Documentation, https://bryanhann.github.io/barking/
Keywords: python
Classifier: Intended Audience :: Developers
Classifier: Programming Language :: Python
Classifier: Programming Language :: Python :: 3
Classifier: Programming Language :: Python :: 3.9
Classifier: Programming Language :: Python :: 3.10
Classifier: Programming Language :: Python :: 3.11
Classifier: Programming Language :: Python :: 3.12
Classifier: Programming Language :: Python :: 3.13
Classifier: Topic :: Software Development :: Libraries :: Python Modules
Requires-Python: <4.0,>=3.9
License-File: LICENSE
